tudthemes/__init__.py
tudthemes/create_common_stylesheet.py
tudthemes/get_address.py
tudthemes/start_notebook.py
tudthemes/themes/bright/custom/custom.css
tudthemes/themes/common/Logo_TU_Dresden.svg
tudthemes/themes/dark/custom/custom.css
tudthemes/themes/default/custom/custom.css
tudthemes-0.1.dist-info/LICENSE
tudthemes-0.1.dist-info/METADATA
tudthemes-0.1.dist-info/WHEEL
tudthemes-0.1.dist-info/top_level.txt
tudthemes-0.1.dist-info/RECORD
