Metadata-Version: 2.1
Name: tudthemes
Version: 0.1
Summary: TU Dresden Corporate Design for Jupyter Notebooks
Home-page: https://github.com/TUD-STKS/tud-themes
Author: Arne-Lukas Fietkau
Author-email: arne-lukas.fietkau@tu-dresden.de
License: MIT
Project-URL: Tracker, https://github.com/TUD-STKS/tud-themes/issues
Keywords: tudthemes
Platform: UNKNOWN
Classifier: Programming Language :: Python :: 3
Classifier: Development Status :: 2 - Pre-Alpha
Classifier: License :: OSI Approved :: BSD License
Classifier: Operating System :: OS Independent
Classifier: Intended Audience :: Science/Research
Requires-Python: >=3.7
Requires-Dist: jupyterlab
